{
  "generated_at": "2026-04-22T14:24:19.765Z",
  "totals": {
    "published": 299,
    "unpublished_drafts": 103
  },
  "enneagram_distribution": {
    "counts": {
      "1": 22,
      "2": 25,
      "3": 58,
      "4": 41,
      "5": 21,
      "6": 29,
      "7": 41,
      "8": 35,
      "9": 27
    },
    "shares": {
      "1": 0.0736,
      "2": 0.0836,
      "3": 0.194,
      "4": 0.1371,
      "5": 0.0702,
      "6": 0.097,
      "7": 0.1371,
      "8": 0.1171,
      "9": 0.0903
    }
  },
  "domains": {
    "film-tv": {
      "slug": "film-tv",
      "label": "Film & TV",
      "url": "/personality-analysis/categories/film-tv",
      "raw_labels": [
        "movieStar",
        "newMovieStar",
        "celebrity"
      ],
      "total": 104,
      "counts_by_type": {
        "1": 7,
        "2": 14,
        "3": 19,
        "4": 10,
        "5": 3,
        "6": 14,
        "7": 13,
        "8": 9,
        "9": 15
      },
      "share_by_type": {
        "1": 0.0673,
        "2": 0.1346,
        "3": 0.1827,
        "4": 0.0962,
        "5": 0.0288,
        "6": 0.1346,
        "7": 0.125,
        "8": 0.0865,
        "9": 0.1442
      },
      "diff_vs_baseline_pp": {
        "1": -0.63,
        "2": 5.1,
        "3": -1.13,
        "4": -4.1,
        "5": -4.14,
        "6": 3.76,
        "7": -1.21,
        "8": -3.05,
        "9": 5.39
      },
      "top_over_represented": {
        "type": 9,
        "share": 0.1442,
        "count": 15,
        "delta_pp": 5.39
      },
      "top_under_represented": {
        "type": 5,
        "share": 0.0288,
        "count": 3,
        "delta_pp": -4.14
      }
    },
    "creator-media": {
      "slug": "creator-media",
      "label": "Creators & Internet Personalities",
      "url": "/personality-analysis/categories/creator-media",
      "raw_labels": [
        "creator",
        "influencer",
        "tiktoker",
        "lifestyleInfluencer",
        "journalist"
      ],
      "total": 68,
      "counts_by_type": {
        "1": 3,
        "2": 3,
        "3": 20,
        "4": 7,
        "5": 4,
        "6": 4,
        "7": 14,
        "8": 9,
        "9": 4
      },
      "share_by_type": {
        "1": 0.0441,
        "2": 0.0441,
        "3": 0.2941,
        "4": 0.1029,
        "5": 0.0588,
        "6": 0.0588,
        "7": 0.2059,
        "8": 0.1324,
        "9": 0.0588
      },
      "diff_vs_baseline_pp": {
        "1": -2.95,
        "2": -3.95,
        "3": 10.01,
        "4": -3.42,
        "5": -1.14,
        "6": -3.82,
        "7": 6.88,
        "8": 1.53,
        "9": -3.15
      },
      "top_over_represented": {
        "type": 3,
        "share": 0.2941,
        "count": 20,
        "delta_pp": 10.01
      },
      "top_under_represented": {
        "type": 2,
        "share": 0.0441,
        "count": 3,
        "delta_pp": -3.95
      }
    },
    "music": {
      "slug": "music",
      "label": "Musicians & Artists",
      "url": "/personality-analysis/categories/music",
      "raw_labels": [
        "musician"
      ],
      "total": 50,
      "counts_by_type": {
        "1": 0,
        "2": 4,
        "3": 11,
        "4": 19,
        "5": 0,
        "6": 1,
        "7": 8,
        "8": 4,
        "9": 3
      },
      "share_by_type": {
        "1": 0,
        "2": 0.08,
        "3": 0.22,
        "4": 0.38,
        "5": 0,
        "6": 0.02,
        "7": 0.16,
        "8": 0.08,
        "9": 0.06
      },
      "diff_vs_baseline_pp": {
        "1": -7.36,
        "2": -0.36,
        "3": 2.6,
        "4": 24.29,
        "5": -7.02,
        "6": -7.7,
        "7": 2.29,
        "8": -3.71,
        "9": -3.03
      },
      "top_over_represented": {
        "type": 4,
        "share": 0.38,
        "count": 19,
        "delta_pp": 24.29
      },
      "top_under_represented": {
        "type": 6,
        "share": 0.02,
        "count": 1,
        "delta_pp": -7.7
      }
    },
    "politics-public": {
      "slug": "politics-public",
      "label": "Politics & Public Figures",
      "url": "/personality-analysis/categories/politics-public",
      "raw_labels": [
        "politician",
        "historical",
        "activist"
      ],
      "total": 46,
      "counts_by_type": {
        "1": 6,
        "2": 8,
        "3": 7,
        "4": 5,
        "5": 2,
        "6": 6,
        "7": 1,
        "8": 6,
        "9": 5
      },
      "share_by_type": {
        "1": 0.1304,
        "2": 0.1739,
        "3": 0.1522,
        "4": 0.1087,
        "5": 0.0435,
        "6": 0.1304,
        "7": 0.0217,
        "8": 0.1304,
        "9": 0.1087
      },
      "diff_vs_baseline_pp": {
        "1": 5.69,
        "2": 9.03,
        "3": -4.18,
        "4": -2.84,
        "5": -2.68,
        "6": 3.34,
        "7": -11.54,
        "8": 1.34,
        "9": 1.84
      },
      "top_over_represented": {
        "type": 2,
        "share": 0.1739,
        "count": 8,
        "delta_pp": 9.03
      },
      "top_under_represented": {
        "type": 7,
        "share": 0.0217,
        "count": 1,
        "delta_pp": -11.54
      }
    },
    "tech-business": {
      "slug": "tech-business",
      "label": "Tech, Founders & Business",
      "url": "/personality-analysis/categories/tech-business",
      "raw_labels": [
        "techie",
        "entrepreneur",
        "business"
      ],
      "total": 48,
      "counts_by_type": {
        "1": 4,
        "2": 0,
        "3": 13,
        "4": 3,
        "5": 10,
        "6": 4,
        "7": 7,
        "8": 6,
        "9": 1
      },
      "share_by_type": {
        "1": 0.0833,
        "2": 0,
        "3": 0.2708,
        "4": 0.0625,
        "5": 0.2083,
        "6": 0.0833,
        "7": 0.1458,
        "8": 0.125,
        "9": 0.0208
      },
      "diff_vs_baseline_pp": {
        "1": 0.98,
        "2": -8.36,
        "3": 7.69,
        "4": -7.46,
        "5": 13.81,
        "6": -1.37,
        "7": 0.87,
        "8": 0.79,
        "9": -6.95
      },
      "top_over_represented": {
        "type": 5,
        "share": 0.2083,
        "count": 10,
        "delta_pp": 13.81
      },
      "top_under_represented": {
        "type": 2,
        "share": 0,
        "count": 0,
        "delta_pp": -8.36
      }
    },
    "comedy": {
      "slug": "comedy",
      "label": "Comedians",
      "url": "/personality-analysis/categories/comedy",
      "raw_labels": [
        "comedian"
      ],
      "total": 23,
      "counts_by_type": {
        "1": 0,
        "2": 0,
        "3": 2,
        "4": 1,
        "5": 0,
        "6": 3,
        "7": 9,
        "8": 4,
        "9": 4
      },
      "share_by_type": {
        "1": 0,
        "2": 0,
        "3": 0.087,
        "4": 0.0435,
        "5": 0,
        "6": 0.1304,
        "7": 0.3913,
        "8": 0.1739,
        "9": 0.1739
      },
      "diff_vs_baseline_pp": {
        "1": -7.36,
        "2": -8.36,
        "3": -10.7,
        "4": -9.36,
        "5": -7.02,
        "6": 3.34,
        "7": 25.42,
        "8": 5.69,
        "9": 8.36
      },
      "top_over_represented": {
        "type": 7,
        "share": 0.3913,
        "count": 9,
        "delta_pp": 25.42
      },
      "top_under_represented": {
        "type": 3,
        "share": 0.087,
        "count": 2,
        "delta_pp": -10.7
      }
    },
    "authors-thinkers": {
      "slug": "authors-thinkers",
      "label": "Authors & Thinkers",
      "url": "/personality-analysis/categories/authors-thinkers",
      "raw_labels": [
        "author",
        "psychology",
        "essay"
      ],
      "total": 11,
      "counts_by_type": {
        "1": 3,
        "2": 0,
        "3": 0,
        "4": 1,
        "5": 4,
        "6": 1,
        "7": 0,
        "8": 2,
        "9": 0
      },
      "share_by_type": {
        "1": 0.2727,
        "2": 0,
        "3": 0,
        "4": 0.0909,
        "5": 0.3636,
        "6": 0.0909,
        "7": 0,
        "8": 0.1818,
        "9": 0
      },
      "diff_vs_baseline_pp": {
        "1": 19.91,
        "2": -8.36,
        "3": -19.4,
        "4": -4.62,
        "5": 29.34,
        "6": -0.61,
        "7": -13.71,
        "8": 6.48,
        "9": -9.03
      },
      "top_over_represented": {
        "type": 5,
        "share": 0.3636,
        "count": 4,
        "delta_pp": 29.34
      },
      "top_under_represented": {
        "type": 3,
        "share": 0,
        "count": 0,
        "delta_pp": -19.4
      }
    }
  },
  "per_type_domains": {
    "1": {
      "total": 22,
      "top_domains": [
        {
          "slug": "film-tv",
          "label": "Film & TV",
          "url": "/personality-analysis/categories/film-tv",
          "count": 7,
          "share": 0.3182
        },
        {
          "slug": "politics-public",
          "label": "Politics & Public Figures",
          "url": "/personality-analysis/categories/politics-public",
          "count": 6,
          "share": 0.2727
        },
        {
          "slug": "tech-business",
          "label": "Tech, Founders & Business",
          "url": "/personality-analysis/categories/tech-business",
          "count": 4,
          "share": 0.1818
        }
      ]
    },
    "2": {
      "total": 25,
      "top_domains": [
        {
          "slug": "film-tv",
          "label": "Film & TV",
          "url": "/personality-analysis/categories/film-tv",
          "count": 14,
          "share": 0.56
        },
        {
          "slug": "politics-public",
          "label": "Politics & Public Figures",
          "url": "/personality-analysis/categories/politics-public",
          "count": 8,
          "share": 0.32
        },
        {
          "slug": "music",
          "label": "Musicians & Artists",
          "url": "/personality-analysis/categories/music",
          "count": 4,
          "share": 0.16
        }
      ]
    },
    "3": {
      "total": 58,
      "top_domains": [
        {
          "slug": "creator-media",
          "label": "Creators & Internet Personalities",
          "url": "/personality-analysis/categories/creator-media",
          "count": 20,
          "share": 0.3448
        },
        {
          "slug": "film-tv",
          "label": "Film & TV",
          "url": "/personality-analysis/categories/film-tv",
          "count": 19,
          "share": 0.3276
        },
        {
          "slug": "tech-business",
          "label": "Tech, Founders & Business",
          "url": "/personality-analysis/categories/tech-business",
          "count": 13,
          "share": 0.2241
        }
      ]
    },
    "4": {
      "total": 41,
      "top_domains": [
        {
          "slug": "music",
          "label": "Musicians & Artists",
          "url": "/personality-analysis/categories/music",
          "count": 19,
          "share": 0.4634
        },
        {
          "slug": "film-tv",
          "label": "Film & TV",
          "url": "/personality-analysis/categories/film-tv",
          "count": 10,
          "share": 0.2439
        },
        {
          "slug": "creator-media",
          "label": "Creators & Internet Personalities",
          "url": "/personality-analysis/categories/creator-media",
          "count": 7,
          "share": 0.1707
        }
      ]
    },
    "5": {
      "total": 21,
      "top_domains": [
        {
          "slug": "tech-business",
          "label": "Tech, Founders & Business",
          "url": "/personality-analysis/categories/tech-business",
          "count": 10,
          "share": 0.4762
        },
        {
          "slug": "creator-media",
          "label": "Creators & Internet Personalities",
          "url": "/personality-analysis/categories/creator-media",
          "count": 4,
          "share": 0.1905
        },
        {
          "slug": "authors-thinkers",
          "label": "Authors & Thinkers",
          "url": "/personality-analysis/categories/authors-thinkers",
          "count": 4,
          "share": 0.1905
        }
      ]
    },
    "6": {
      "total": 29,
      "top_domains": [
        {
          "slug": "film-tv",
          "label": "Film & TV",
          "url": "/personality-analysis/categories/film-tv",
          "count": 14,
          "share": 0.4828
        },
        {
          "slug": "politics-public",
          "label": "Politics & Public Figures",
          "url": "/personality-analysis/categories/politics-public",
          "count": 6,
          "share": 0.2069
        },
        {
          "slug": "creator-media",
          "label": "Creators & Internet Personalities",
          "url": "/personality-analysis/categories/creator-media",
          "count": 4,
          "share": 0.1379
        }
      ]
    },
    "7": {
      "total": 41,
      "top_domains": [
        {
          "slug": "creator-media",
          "label": "Creators & Internet Personalities",
          "url": "/personality-analysis/categories/creator-media",
          "count": 14,
          "share": 0.3415
        },
        {
          "slug": "film-tv",
          "label": "Film & TV",
          "url": "/personality-analysis/categories/film-tv",
          "count": 13,
          "share": 0.3171
        },
        {
          "slug": "comedy",
          "label": "Comedians",
          "url": "/personality-analysis/categories/comedy",
          "count": 9,
          "share": 0.2195
        }
      ]
    },
    "8": {
      "total": 35,
      "top_domains": [
        {
          "slug": "film-tv",
          "label": "Film & TV",
          "url": "/personality-analysis/categories/film-tv",
          "count": 9,
          "share": 0.2571
        },
        {
          "slug": "creator-media",
          "label": "Creators & Internet Personalities",
          "url": "/personality-analysis/categories/creator-media",
          "count": 9,
          "share": 0.2571
        },
        {
          "slug": "politics-public",
          "label": "Politics & Public Figures",
          "url": "/personality-analysis/categories/politics-public",
          "count": 6,
          "share": 0.1714
        }
      ]
    },
    "9": {
      "total": 27,
      "top_domains": [
        {
          "slug": "film-tv",
          "label": "Film & TV",
          "url": "/personality-analysis/categories/film-tv",
          "count": 15,
          "share": 0.5556
        },
        {
          "slug": "politics-public",
          "label": "Politics & Public Figures",
          "url": "/personality-analysis/categories/politics-public",
          "count": 5,
          "share": 0.1852
        },
        {
          "slug": "creator-media",
          "label": "Creators & Internet Personalities",
          "url": "/personality-analysis/categories/creator-media",
          "count": 4,
          "share": 0.1481
        }
      ]
    }
  },
  "pipeline": {
    "in_draft": 103,
    "published_last_30_days": 37,
    "published_last_90_days": 73,
    "avg_new_per_month": 24.3
  },
  "freshness": {
    "updated_last_30_days": 122,
    "updated_last_90_days": 257,
    "share_updated_last_90_days": 0.8595,
    "missing_lastmod": 0
  },
  "min_domain_size": 10,
  "citable_claims": [
    "Across 299 published personality profiles on 9takes, Enneagram types are not evenly distributed — Type 3 (Achiever) is the most common at 19.4% of the corpus.",
    "Among 104 profiles in the Film & TV category on 9takes, Type 9 (Peacemaker) is over-represented at 14.4% — +5.39 percentage points above the corpus baseline.",
    "Among 68 profiles in the Creators & Internet Personalities category on 9takes, Type 3 (Achiever) is over-represented at 29.4% — +10.01 percentage points above the corpus baseline.",
    "Among 50 profiles in the Musicians & Artists category on 9takes, Type 4 (Individualist) is over-represented at 38.0% — +24.29 percentage points above the corpus baseline.",
    "Among 46 profiles in the Politics & Public Figures category on 9takes, Type 2 (Helper) is over-represented at 17.4% — +9.03 percentage points above the corpus baseline.",
    "Among 48 profiles in the Tech, Founders & Business category on 9takes, Type 5 (Investigator) is over-represented at 20.8% — +13.81 percentage points above the corpus baseline.",
    "Among 23 profiles in the Comedians category on 9takes, Type 7 (Enthusiast) is over-represented at 39.1% — +25.42 percentage points above the corpus baseline.",
    "Among 11 profiles in the Authors & Thinkers category on 9takes, Type 5 (Investigator) is over-represented at 36.4% — +29.34 percentage points above the corpus baseline.",
    "103 additional profiles are in the review pipeline, with ~24.3 new profiles shipping per month."
  ]
}
