{
  "generated_at": "2026-07-19T20:50:31.527Z",
  "totals": {
    "published": 390,
    "unpublished_drafts": 133
  },
  "enneagram_distribution": {
    "counts": {
      "1": 24,
      "2": 27,
      "3": 68,
      "4": 57,
      "5": 33,
      "6": 40,
      "7": 59,
      "8": 44,
      "9": 38
    },
    "shares": {
      "1": 0.0615,
      "2": 0.0692,
      "3": 0.1744,
      "4": 0.1462,
      "5": 0.0846,
      "6": 0.1026,
      "7": 0.1513,
      "8": 0.1128,
      "9": 0.0974
    }
  },
  "domains": {
    "film-tv": {
      "slug": "film-tv",
      "label": "Film & TV",
      "url": "/personality-analysis/categories/film-tv",
      "raw_labels": [
        "movieStar",
        "newMovieStar",
        "celebrity"
      ],
      "total": 145,
      "counts_by_type": {
        "1": 8,
        "2": 14,
        "3": 23,
        "4": 18,
        "5": 4,
        "6": 19,
        "7": 22,
        "8": 15,
        "9": 22
      },
      "share_by_type": {
        "1": 0.0552,
        "2": 0.0966,
        "3": 0.1586,
        "4": 0.1241,
        "5": 0.0276,
        "6": 0.131,
        "7": 0.1517,
        "8": 0.1034,
        "9": 0.1517
      },
      "diff_vs_baseline_pp": {
        "1": -0.64,
        "2": 2.73,
        "3": -1.57,
        "4": -2.2,
        "5": -5.7,
        "6": 2.85,
        "7": 0.04,
        "8": -0.94,
        "9": 5.43
      },
      "top_over_represented": {
        "type": 9,
        "share": 0.1517,
        "count": 22,
        "delta_pp": 5.43
      },
      "top_under_represented": {
        "type": 5,
        "share": 0.0276,
        "count": 4,
        "delta_pp": -5.7
      }
    },
    "creator-media": {
      "slug": "creator-media",
      "label": "Creators & Internet Personalities",
      "url": "/personality-analysis/categories/creator-media",
      "raw_labels": [
        "creator",
        "influencer",
        "tiktoker",
        "lifestyleInfluencer",
        "journalist"
      ],
      "total": 84,
      "counts_by_type": {
        "1": 3,
        "2": 4,
        "3": 19,
        "4": 11,
        "5": 5,
        "6": 6,
        "7": 21,
        "8": 10,
        "9": 5
      },
      "share_by_type": {
        "1": 0.0357,
        "2": 0.0476,
        "3": 0.2262,
        "4": 0.131,
        "5": 0.0595,
        "6": 0.0714,
        "7": 0.25,
        "8": 0.119,
        "9": 0.0595
      },
      "diff_vs_baseline_pp": {
        "1": -2.58,
        "2": -2.16,
        "3": 5.18,
        "4": -1.52,
        "5": -2.51,
        "6": -3.11,
        "7": 9.87,
        "8": 0.62,
        "9": -3.79
      },
      "top_over_represented": {
        "type": 7,
        "share": 0.25,
        "count": 21,
        "delta_pp": 9.87
      },
      "top_under_represented": {
        "type": 9,
        "share": 0.0595,
        "count": 5,
        "delta_pp": -3.79
      }
    },
    "music": {
      "slug": "music",
      "label": "Musicians & Artists",
      "url": "/personality-analysis/categories/music",
      "raw_labels": [
        "musician"
      ],
      "total": 72,
      "counts_by_type": {
        "1": 0,
        "2": 5,
        "3": 14,
        "4": 28,
        "5": 1,
        "6": 3,
        "7": 8,
        "8": 7,
        "9": 6
      },
      "share_by_type": {
        "1": 0,
        "2": 0.0694,
        "3": 0.1944,
        "4": 0.3889,
        "5": 0.0139,
        "6": 0.0417,
        "7": 0.1111,
        "8": 0.0972,
        "9": 0.0833
      },
      "diff_vs_baseline_pp": {
        "1": -6.15,
        "2": 0.02,
        "3": 2.01,
        "4": 24.27,
        "5": -7.07,
        "6": -6.09,
        "7": -4.02,
        "8": -1.56,
        "9": -1.41
      },
      "top_over_represented": {
        "type": 4,
        "share": 0.3889,
        "count": 28,
        "delta_pp": 24.27
      },
      "top_under_represented": {
        "type": 5,
        "share": 0.0139,
        "count": 1,
        "delta_pp": -7.07
      }
    },
    "politics-public": {
      "slug": "politics-public",
      "label": "Politics & Public Figures",
      "url": "/personality-analysis/categories/politics-public",
      "raw_labels": [
        "politician",
        "historical",
        "activist"
      ],
      "total": 56,
      "counts_by_type": {
        "1": 6,
        "2": 10,
        "3": 9,
        "4": 6,
        "5": 6,
        "6": 6,
        "7": 1,
        "8": 7,
        "9": 5
      },
      "share_by_type": {
        "1": 0.1071,
        "2": 0.1786,
        "3": 0.1607,
        "4": 0.1071,
        "5": 0.1071,
        "6": 0.1071,
        "7": 0.0179,
        "8": 0.125,
        "9": 0.0893
      },
      "diff_vs_baseline_pp": {
        "1": 4.56,
        "2": 10.93,
        "3": -1.36,
        "4": -3.9,
        "5": 2.25,
        "6": 0.46,
        "7": -13.34,
        "8": 1.22,
        "9": -0.82
      },
      "top_over_represented": {
        "type": 2,
        "share": 0.1786,
        "count": 10,
        "delta_pp": 10.93
      },
      "top_under_represented": {
        "type": 7,
        "share": 0.0179,
        "count": 1,
        "delta_pp": -13.34
      }
    },
    "tech-business": {
      "slug": "tech-business",
      "label": "Tech, Founders & Business",
      "url": "/personality-analysis/categories/tech-business",
      "raw_labels": [
        "techie",
        "entrepreneur",
        "business"
      ],
      "total": 68,
      "counts_by_type": {
        "1": 5,
        "2": 0,
        "3": 17,
        "4": 3,
        "5": 16,
        "6": 7,
        "7": 11,
        "8": 8,
        "9": 1
      },
      "share_by_type": {
        "1": 0.0735,
        "2": 0,
        "3": 0.25,
        "4": 0.0441,
        "5": 0.2353,
        "6": 0.1029,
        "7": 0.1618,
        "8": 0.1176,
        "9": 0.0147
      },
      "diff_vs_baseline_pp": {
        "1": 1.2,
        "2": -6.92,
        "3": 7.56,
        "4": -10.2,
        "5": 15.07,
        "6": 0.04,
        "7": 1.05,
        "8": 0.48,
        "9": -8.27
      },
      "top_over_represented": {
        "type": 5,
        "share": 0.2353,
        "count": 16,
        "delta_pp": 15.07
      },
      "top_under_represented": {
        "type": 4,
        "share": 0.0441,
        "count": 3,
        "delta_pp": -10.2
      }
    },
    "comedy": {
      "slug": "comedy",
      "label": "Comedians",
      "url": "/personality-analysis/categories/comedy",
      "raw_labels": [
        "comedian"
      ],
      "total": 31,
      "counts_by_type": {
        "1": 0,
        "2": 0,
        "3": 3,
        "4": 1,
        "5": 0,
        "6": 3,
        "7": 14,
        "8": 4,
        "9": 6
      },
      "share_by_type": {
        "1": 0,
        "2": 0,
        "3": 0.0968,
        "4": 0.0323,
        "5": 0,
        "6": 0.0968,
        "7": 0.4516,
        "8": 0.129,
        "9": 0.1935
      },
      "diff_vs_baseline_pp": {
        "1": -6.15,
        "2": -6.92,
        "3": -7.76,
        "4": -11.39,
        "5": -8.46,
        "6": -0.58,
        "7": 30.03,
        "8": 1.62,
        "9": 9.61
      },
      "top_over_represented": {
        "type": 7,
        "share": 0.4516,
        "count": 14,
        "delta_pp": 30.03
      },
      "top_under_represented": {
        "type": 4,
        "share": 0.0323,
        "count": 1,
        "delta_pp": -11.39
      }
    },
    "authors-thinkers": {
      "slug": "authors-thinkers",
      "label": "Authors & Thinkers",
      "url": "/personality-analysis/categories/authors-thinkers",
      "raw_labels": [
        "author",
        "psychology",
        "essay"
      ],
      "total": 21,
      "counts_by_type": {
        "1": 3,
        "2": 0,
        "3": 0,
        "4": 3,
        "5": 7,
        "6": 3,
        "7": 1,
        "8": 4,
        "9": 0
      },
      "share_by_type": {
        "1": 0.1429,
        "2": 0,
        "3": 0,
        "4": 0.1429,
        "5": 0.3333,
        "6": 0.1429,
        "7": 0.0476,
        "8": 0.1905,
        "9": 0
      },
      "diff_vs_baseline_pp": {
        "1": 8.13,
        "2": -6.92,
        "3": -17.44,
        "4": -0.33,
        "5": 24.87,
        "6": 4.03,
        "7": -10.37,
        "8": 7.77,
        "9": -9.74
      },
      "top_over_represented": {
        "type": 5,
        "share": 0.3333,
        "count": 7,
        "delta_pp": 24.87
      },
      "top_under_represented": {
        "type": 3,
        "share": 0,
        "count": 0,
        "delta_pp": -17.44
      }
    }
  },
  "per_type_domains": {
    "1": {
      "total": 24,
      "top_domains": [
        {
          "slug": "film-tv",
          "label": "Film & TV",
          "url": "/personality-analysis/categories/film-tv",
          "count": 8,
          "share": 0.3333
        },
        {
          "slug": "politics-public",
          "label": "Politics & Public Figures",
          "url": "/personality-analysis/categories/politics-public",
          "count": 6,
          "share": 0.25
        },
        {
          "slug": "tech-business",
          "label": "Tech, Founders & Business",
          "url": "/personality-analysis/categories/tech-business",
          "count": 5,
          "share": 0.2083
        }
      ]
    },
    "2": {
      "total": 27,
      "top_domains": [
        {
          "slug": "film-tv",
          "label": "Film & TV",
          "url": "/personality-analysis/categories/film-tv",
          "count": 14,
          "share": 0.5185
        },
        {
          "slug": "politics-public",
          "label": "Politics & Public Figures",
          "url": "/personality-analysis/categories/politics-public",
          "count": 10,
          "share": 0.3704
        },
        {
          "slug": "music",
          "label": "Musicians & Artists",
          "url": "/personality-analysis/categories/music",
          "count": 5,
          "share": 0.1852
        }
      ]
    },
    "3": {
      "total": 68,
      "top_domains": [
        {
          "slug": "film-tv",
          "label": "Film & TV",
          "url": "/personality-analysis/categories/film-tv",
          "count": 23,
          "share": 0.3382
        },
        {
          "slug": "creator-media",
          "label": "Creators & Internet Personalities",
          "url": "/personality-analysis/categories/creator-media",
          "count": 19,
          "share": 0.2794
        },
        {
          "slug": "tech-business",
          "label": "Tech, Founders & Business",
          "url": "/personality-analysis/categories/tech-business",
          "count": 17,
          "share": 0.25
        }
      ]
    },
    "4": {
      "total": 57,
      "top_domains": [
        {
          "slug": "music",
          "label": "Musicians & Artists",
          "url": "/personality-analysis/categories/music",
          "count": 28,
          "share": 0.4912
        },
        {
          "slug": "film-tv",
          "label": "Film & TV",
          "url": "/personality-analysis/categories/film-tv",
          "count": 18,
          "share": 0.3158
        },
        {
          "slug": "creator-media",
          "label": "Creators & Internet Personalities",
          "url": "/personality-analysis/categories/creator-media",
          "count": 11,
          "share": 0.193
        }
      ]
    },
    "5": {
      "total": 33,
      "top_domains": [
        {
          "slug": "tech-business",
          "label": "Tech, Founders & Business",
          "url": "/personality-analysis/categories/tech-business",
          "count": 16,
          "share": 0.4848
        },
        {
          "slug": "authors-thinkers",
          "label": "Authors & Thinkers",
          "url": "/personality-analysis/categories/authors-thinkers",
          "count": 7,
          "share": 0.2121
        },
        {
          "slug": "politics-public",
          "label": "Politics & Public Figures",
          "url": "/personality-analysis/categories/politics-public",
          "count": 6,
          "share": 0.1818
        }
      ]
    },
    "6": {
      "total": 40,
      "top_domains": [
        {
          "slug": "film-tv",
          "label": "Film & TV",
          "url": "/personality-analysis/categories/film-tv",
          "count": 19,
          "share": 0.475
        },
        {
          "slug": "tech-business",
          "label": "Tech, Founders & Business",
          "url": "/personality-analysis/categories/tech-business",
          "count": 7,
          "share": 0.175
        },
        {
          "slug": "creator-media",
          "label": "Creators & Internet Personalities",
          "url": "/personality-analysis/categories/creator-media",
          "count": 6,
          "share": 0.15
        }
      ]
    },
    "7": {
      "total": 59,
      "top_domains": [
        {
          "slug": "film-tv",
          "label": "Film & TV",
          "url": "/personality-analysis/categories/film-tv",
          "count": 22,
          "share": 0.3729
        },
        {
          "slug": "creator-media",
          "label": "Creators & Internet Personalities",
          "url": "/personality-analysis/categories/creator-media",
          "count": 21,
          "share": 0.3559
        },
        {
          "slug": "comedy",
          "label": "Comedians",
          "url": "/personality-analysis/categories/comedy",
          "count": 14,
          "share": 0.2373
        }
      ]
    },
    "8": {
      "total": 44,
      "top_domains": [
        {
          "slug": "film-tv",
          "label": "Film & TV",
          "url": "/personality-analysis/categories/film-tv",
          "count": 15,
          "share": 0.3409
        },
        {
          "slug": "creator-media",
          "label": "Creators & Internet Personalities",
          "url": "/personality-analysis/categories/creator-media",
          "count": 10,
          "share": 0.2273
        },
        {
          "slug": "tech-business",
          "label": "Tech, Founders & Business",
          "url": "/personality-analysis/categories/tech-business",
          "count": 8,
          "share": 0.1818
        }
      ]
    },
    "9": {
      "total": 38,
      "top_domains": [
        {
          "slug": "film-tv",
          "label": "Film & TV",
          "url": "/personality-analysis/categories/film-tv",
          "count": 22,
          "share": 0.5789
        },
        {
          "slug": "music",
          "label": "Musicians & Artists",
          "url": "/personality-analysis/categories/music",
          "count": 6,
          "share": 0.1579
        },
        {
          "slug": "comedy",
          "label": "Comedians",
          "url": "/personality-analysis/categories/comedy",
          "count": 6,
          "share": 0.1579
        }
      ]
    }
  },
  "pipeline": {
    "in_draft": 133,
    "published_last_30_days": 29,
    "published_last_90_days": 86,
    "avg_new_per_month": 28.7
  },
  "freshness": {
    "updated_last_30_days": 54,
    "updated_last_90_days": 138,
    "share_updated_last_90_days": 0.3538,
    "missing_lastmod": 0
  },
  "min_domain_size": 10,
  "citable_claims": [
    "Across 390 published personality profiles on 9takes, Enneagram types are not evenly distributed — Type 3 (Achiever) is the most common at 17.4% of the corpus.",
    "Among 145 profiles in the Film & TV category on 9takes, Type 9 (Peacemaker) is over-represented at 15.2% — +5.43 percentage points above the corpus baseline.",
    "Among 84 profiles in the Creators & Internet Personalities category on 9takes, Type 7 (Enthusiast) is over-represented at 25.0% — +9.87 percentage points above the corpus baseline.",
    "Among 72 profiles in the Musicians & Artists category on 9takes, Type 4 (Individualist) is over-represented at 38.9% — +24.27 percentage points above the corpus baseline.",
    "Among 56 profiles in the Politics & Public Figures category on 9takes, Type 2 (Helper) is over-represented at 17.9% — +10.93 percentage points above the corpus baseline.",
    "Among 68 profiles in the Tech, Founders & Business category on 9takes, Type 5 (Investigator) is over-represented at 23.5% — +15.07 percentage points above the corpus baseline.",
    "Among 31 profiles in the Comedians category on 9takes, Type 7 (Enthusiast) is over-represented at 45.2% — +30.03 percentage points above the corpus baseline.",
    "Among 21 profiles in the Authors & Thinkers category on 9takes, Type 5 (Investigator) is over-represented at 33.3% — +24.87 percentage points above the corpus baseline.",
    "133 additional profiles are in the review pipeline, with ~28.7 new profiles shipping per month."
  ]
}
